livelogs/__init__.py
livelogs/app.py
livelogs/static/script.js
livelogs/static/style.css
livelogs/templates/index.html
livelogs-0.1.6.dist-info/METADATA
livelogs-0.1.6.dist-info/WHEEL
livelogs-0.1.6.dist-info/entry_points.txt
livelogs-0.1.6.dist-info/RECORD
