Metadata-Version: 2.1
Name: livelogs
Version: 0.1.6
Summary: A live log streaming application
Home-page: https://github.com/destinedcodes/livelogs
License: MIT
Keywords: log,logs,livelogs
Author: Destiny Saturday
Author-email: destiny@destinedcodes.com
Requires-Python: >=3.8,<4.0
Classifier: License :: OSI Approved :: MIT License
Classifier: Operating System :: OS Independent
Classifier: Programming Language :: Python :: 3
Classifier: Programming Language :: Python :: 3.8
Classifier: Programming Language :: Python :: 3.9
Classifier: Programming Language :: Python :: 3.10
Classifier: Programming Language :: Python :: 3.11
Classifier: Programming Language :: Python :: 3.12
Requires-Dist: bidict (>=0.23.1,<0.24.0)
Requires-Dist: blinker (>=1.8.2,<2.0.0)
Requires-Dist: cryptography (>=43.0.0,<44.0.0)
Requires-Dist: dnspython (>=2.6.1,<3.0.0)
Requires-Dist: eventlet (>=0.36.1,<0.37.0)
Requires-Dist: flask (>=3.0.3,<4.0.0)
Requires-Dist: flask-socketio (>=5.3.6,<6.0.0)
Requires-Dist: greenlet (>=3.0.3,<4.0.0)
Requires-Dist: h11 (>=0.14.0,<0.15.0)
Requires-Dist: itsdangerous (>=2.2.0,<3.0.0)
Requires-Dist: jinja2 (>=3.1.4,<4.0.0)
Requires-Dist: markupsafe (>=2.1.5,<3.0.0)
Requires-Dist: pyopenssl (>=24.2.1,<25.0.0)
Requires-Dist: python-engineio (>=4.9.1,<5.0.0)
Requires-Dist: python-socketio (>=5.11.3,<6.0.0)
Requires-Dist: simple-websocket (>=1.0.0,<2.0.0)
Requires-Dist: werkzeug (>=3.0.3,<4.0.0)
Requires-Dist: wsproto (>=1.2.0,<2.0.0)
Project-URL: Documentation, https://github.com/destinedcodes/livelogs#readme
Project-URL: Repository, https://github.com/destinedcodes/livelogs
